Workbook

Sheet Retos
A1: id | B1: texto | C1: variante_corta | D1: virtud | E1: subcomponente | F1: facultad | G1: ambito | H1: tipo | I1: intensidad | J1: minutos_estimados | K1: requiere_otra_persona | L1: disparador_contextual | M1: dif_colerico | N1: dif_melancolico | O1: dif_sanguineo | P1: dif_flematico | Q1: obstaculo_que_combate | R1: repetible | S1: pregunta_examen | T1: fuente_libro | U1: fuente_seccion | V1: cita_literal
A2: pru-01 | B2: Antes de tomar hoy una decisión que afecte a otros, pide la opinión de al menos una persona y escúchala hasta el final sin interrumpir. | C2: Pide consejo antes de decidir | D2: prudencia | E2: deliberacion | F2: razon | G2: trabajo | H2: accion | I2: =ROUND(AVERAGE(M2:P2),0) -> 3 | J2: 10 | K2: sí | L2: reunión o decisión del día | M2: 5 | N2: 2 | O2: 3 | P2: 2 | Q2: autosatisfacción | R2: sí | S2: ¿Pedí consejo antes de decidir? Si no, ¿fue por prisa (primera reacción) o porque decidí no hacerlo? | T2: Del temperamento al carácter | U2: 3. El colérico: su desafío personal | V2: debe aprender a pedir consejo de forma habitual
A3: pru-02 | B3: Hoy toma una decisión que llevas aplazando. Fija la hora, decide y comunícala, aunque no tengas toda la información. | C3: Decide hoy lo aplazado | D3: prudencia | E3: decision | F3: razon | G3: trabajo | H3: accion | I3: =ROUND(AVERAGE(M3:P3),0) -> 3 | J3: 15 | K3: no | L3: asunto pendiente que se arrastra | M3: 1 | N3: 5 | O3: 2 | P3: 5 | Q3: perfeccionismo | R3: sí | S3: ¿Decidí? Si no, ¿qué certeza estaba esperando y era razonable esperarla? | T3: Del temperamento al carácter | U3: 4. El melancólico: su desafío personal | V3: El objetivo de la prudencia no es deliberar, sino decidir
A4: pru-03 | B4: Antes de dar por buena una información importante hoy, pregúntate de dónde viene y si es un hecho o una opinión. Anótalo. | C4: Distingue hechos de opiniones | D4: prudencia | E4: deliberacion | F4: razon | G4: trabajo | H4: accion | I4: =ROUND(AVERAGE(M4:P4),0) -> 3 | J4: 5 | K4: no | L4: noticia, informe o rumor recibido | M4: 3 | N4: 2 | O4: 4 | P4: 2 | R4: sí | S4: ¿Separé hechos de opiniones antes de decidir o repetí lo que oí? | T4: Creado para la grandeza | U4: Pasos prácticos: Prudencia | V4: ¿Hago distinciones entre hechos y opiniones, verdades y medias verdades?
A5: pru-04 | B5: Identifica hoy una verdad incómoda que estás evitando mirar (sobre un proyecto, una relación, tu salud). Escríbela en una frase. | C5: Mira la verdad incómoda | D5: prudencia | E5: deliberacion | F5: razon | G5: vida interior | H5: contemplacion | I5: =ROUND(AVERAGE(M5:P5),0) -> 3 | J5: 10 | K5: no | M5: 3 | N5: 2 | O5: 4 | P5: 3 | Q5: conformismo | R5: no | S5: ¿Escribí la verdad incómoda tal como es, sin suavizarla? | T5: Creado para la grandeza | U5: Pasos prácticos: Prudencia | V5: ¿Rechazo las verdades que me cuesta aceptar?
A6: pru-05 | B6: Cuando algo salga mal hoy, nombra tu parte de responsabilidad en voz alta o por escrito antes de hablar de la de los demás. | C6: Asume tu parte primero | D6: prudencia | E6: decision | F6: razon | G6: trabajo | H6: accion | I6: =ROUND(AVERAGE(M6:P6),0) -> 3 | J6: 5 | K6: sí | L6: error o contratiempo | M6: 5 | N6: 2 | O6: 3 | P6: 2 | R6: sí | S6: ¿Nombré mi responsabilidad antes de señalar a otros? | T6: Creado para la grandeza | U6: Pasos prácticos: Prudencia | V6: Si las cosas van mal, ¿evito acusar a los demás?
A7: pru-06 | B7: Hoy, antes de responder a una propuesta ajena, repite con tus palabras lo que la otra persona ha dicho y pregúntale si lo has entendido bien. | C7: Repite antes de responder | D7: prudencia | E7: deliberacion | F7: razon | G7: trabajo | H7: accion | I7: =ROUND(AVERAGE(M7:P7),0) -> 3 | J7: 5 | K7: sí | L7: conversación con desacuerdo | M7: 5 | N7: 3 | O7: 3 | P7: 2 | R7: sí | S7: ¿Comprobé que había entendido antes de responder? | T7: Del temperamento al carácter | U7: 3. El colérico: su desafío personal | V7: Precisa humildad para escuchar a las personas y comprenderlas
A8: pru-07 | B8: Elige una decisión pequeña que te esté costando y date un límite: diez minutos de reflexión y luego actúa, pase lo que pase. | C8: Diez minutos y actúa | D8: prudencia | E8: decision | F8: razon | G8: trabajo | H8: accion | I8: =ROUND(AVERAGE(M8:P8),0) -> 3 | J8: 10 | K8: no | L8: indecisión ante algo menor | M8: 1 | N8: 5 | O8: 2 | P8: 5 | Q8: perfeccionismo | R8: sí | S8: ¿Respeté el límite de tiempo y actué? | T8: Del temperamento al carácter | U8: 4. El melancólico: su desafío personal | V8: Hamlet siempre le falta información
A9: pru-08 | B9: Pregunta hoy a alguien con más experiencia cómo resolvió una situación parecida a la que tienes entre manos. | C9: Aprende de la experiencia ajena | D9: prudencia | E9: deliberacion | F9: razon | G9: trabajo | H9: accion | I9: =ROUND(AVERAGE(M9:P9),0) -> 3 | J9: 15 | K9: sí | L9: problema nuevo | M9: 4 | N9: 3 | O9: 2 | P9: 2 | Q9: autosatisfacción | R9: sí | S9: ¿Pregunté y escuché, o preferí resolverlo solo? | T9: Creado para la grandeza | U9: Pasos prácticos: Prudencia | V9: ¿Soy lo bastante humilde como para aprender de la experiencia ajena?
A10: pru-09 | B10: Antes de una decisión de hoy, enumera por escrito las tres dificultades reales y tacha las que solo existen en tu imaginación. | C10: Tacha los problemas imaginarios | D10: prudencia | E10: deliberacion | F10: razon | G10: vida interior | H10: contemplacion | I10: =ROUND(AVERAGE(M10:P10),0) -> 3 | J10: 10 | K10: no | L10: preocupación recurrente | M10: 2 | N10: 5 | O10: 2 | P10: 4 | R10: sí | S10: ¿Cuántas dificultades quedaron tras tachar? ¿Era tan grave como sentía? | T10: Del temperamento al carácter | U10: 4. El melancólico: su desafío personal | V10: El 90% de los problemas que me hacen sentir mal solo existen en mi imaginación
A11: pru-10 | B11: Hoy, en un asunto donde estás seguro de tener razón, busca activamente un dato o argumento que te contradiga. | C11: Busca lo que te contradice | D11: prudencia | E11: deliberacion | F11: razon | G11: trabajo | H11: accion | I11: =ROUND(AVERAGE(M11:P11),0) -> 3 | J11: 10 | K11: no | L11: convicción fuerte | M11: 5 | N11: 3 | O11: 3 | P11: 2 | R11: sí | S11: ¿Encontré algo que me contradijera y lo tuve en cuenta? | T11: Creado para la grandeza | U11: Pasos prácticos: Prudencia | V11: ¿Soy suficientemente humilde como para reconocer y dejar a un lado mis prejuicios?
A12: pru-11 | B12: Antes de aceptar una propuesta que te entusiasma, enumera tres razones por las que podría no funcionar. | C12: Enfría el entusiasmo con datos | D12: prudencia | E12: deliberacion | F12: razon | G12: trabajo | H12: accion | I12: =ROUND(AVERAGE(M12:P12),0) -> 3 | J12: 10 | K12: no | L12: propuesta atractiva | M12: 3 | N12: 1 | O12: 5 | P12: 2 | R12: sí | S12: ¿Pensé seriamente en lo que podía fallar o dije 'esto va a funcionar' sin más? | T12: Del temperamento al carácter | U12: 5. El sanguíneo: su desafío personal | V12: debe esforzarse por vencer la superficialidad
A13: pru-12 | B13: Una vez tomada una decisión hoy, ponla en marcha antes de que acabe el día: un correo, una llamada, un primer paso. | C13: Ejecuta la decisión hoy | D13: prudencia | E13: decision | F13: razon | G13: trabajo | H13: accion | I13: =ROUND(AVERAGE(M13:P13),0) -> 3 | J13: 15 | K13: no | L13: decisión reciente | M13: 1 | N13: 4 | O13: 3 | P13: 4 | R13: sí | S13: ¿Di el primer paso el mismo día? | T13: Del temperamento al carácter | U13: 7. Desarrollo de la audacia | V13: No tardes en poner por obra tus decisiones
A14: aud-01 | B14: Hoy propón en voz alta una idea que llevas tiempo guardando, en una reunión o a alguien con capacidad de decidir. | C14: Di la idea que guardas | D14: fortaleza | E14: audacia | F14: voluntad | G14: trabajo | H14: accion | I14: =ROUND(AVERAGE(M14:P14),0) -> 3 | J14: 5 | K14: sí | L14: reunión de equipo | M14: 1 | N14: 5 | O14: 2 | P14: 4 | Q14: conformismo | R14: no | S14: ¿Dije mi idea? Si no, ¿qué temía exactamente? | T14: Del temperamento al carácter | U14: 7. Desarrollo de la audacia | V14: Comparte con todo el mundo lo que tienes en tu interior
A15: aud-02 | B15: Inicia hoy una conversación con alguien que no conoces o con quien hace tiempo que no hablas. | C15: Habla con alguien nuevo | D15: fortaleza | E15: audacia | F15: voluntad | G15: amistad | H15: accion | I15: =ROUND(AVERAGE(M15:P15),0) -> 3 | J15: 10 | K15: sí | M15: 1 | N15: 5 | O15: 1 | P15: 4 | R15: sí | S15: ¿Fui yo quien inició la conversación? | T15: Del temperamento al carácter | U15: 7. Desarrollo de la audacia | V15: No te aísles. Ve al encuentro de la gente
A16: aud-03 | B16: Toma hoy una decisión que implique un riesgo razonable en tu vida profesional y que venías evitando por miedo a equivocarte. | C16: Asume un riesgo razonable | D16: fortaleza | E16: audacia | F16: voluntad | G16: trabajo | H16: accion | I16: =ROUND(AVERAGE(M16:P16),0) -> 3 | J16: 20 | K16: no | L16: oportunidad que da miedo | M16: 1 | N16: 5 | O16: 2 | P16: 5 | Q16: perfeccionismo | R16: no | S16: ¿Asumí el riesgo? ¿Lo que me frenaba era prudencia o miedo a equivocarme? | T16: Del temperamento al carácter | U16: 6. El flemático: su desafío personal | V16: Debe practicar la audacia, porque la esencia de la prudencia no es la deliberación, sino la decisión
A17: aud-04 | B17: Hoy trata de frente un asunto difícil con una persona concreta, en lugar de rodearlo o posponerlo. | C17: Trata lo difícil de frente | D17: fortaleza | E17: audacia | F17: voluntad | G17: trabajo | H17: accion | I17: =ROUND(AVERAGE(M17:P17),0) -> 4 | J17: 15 | K17: sí | L17: conflicto latente | M17: 1 | N17: 4 | O17: 4 | P17: 5 | Q17: conformismo | R17: sí | S17: ¿Abordé el asunto directamente? | T17: Creado para la grandeza | U17: Pasos prácticos: Fortaleza | V17: ¿Reúno el valor para tratar directamente asuntos difíciles?
A18: aud-05 | B18: Escribe tu misión en una frase y léela en voz alta antes de empezar el día. Si no la tienes, escribe hoy un primer borrador. | C18: Lee tu misión en voz alta | D18: fortaleza | E18: audacia | F18: voluntad | G18: vida interior | H18: contemplacion | I18: =ROUND(AVERAGE(M18:P18),0) -> 3 | J18: 5 | K18: no | L18: inicio del día | M18: 2 | N18: 3 | O18: 3 | P18: 4 | R18: sí | S18: ¿Recordé mi misión y cambió algo en cómo actué? | T18: Del temperamento al carácter | U18: 7. Desarrollo de la audacia | V18: Transforma tu sueño en misión y recuérdate esta misión cada día
A19: aud-06 | B19: Comete hoy un error a propósito de ser rápido: entrega, publica o envía algo al 80 % de perfección en lugar de pulirlo más. | C19: Entrega al 80 % | D19: fortaleza | E19: audacia | F19: voluntad | G19: trabajo | H19: accion | I19: =ROUND(AVERAGE(M19:P19),0) -> 3 | J19: 15 | K19: no | L19: tarea que llevas puliendo | M19: 1 | N19: 5 | O19: 2 | P19: 4 | Q19: perfeccionismo | R19: sí | S19: ¿Entregué sin esperar la perfección? ¿Qué pasó? | T19: Del temperamento al carácter | U19: 4. El melancólico: su desafío personal | V19: Cuanto mejor es un hombre, tantos más errores comete
A20: aud-07 | B20: Defiende hoy tu punto de vista ante alguien con más autoridad que tú, con respeto y sin ceder por comodidad. | C20: Defiende tu postura ante autoridad | D20: fortaleza | E20: audacia | F20: voluntad | G20: trabajo | H20: accion | I20: =ROUND(AVERAGE(M20:P20),0) -> 4 | J20: 10 | K20: sí | L20: desacuerdo con un superior | M20: 2 | N20: 4 | O20: 3 | P20: 5 | Q20: conformismo | R20: no | S20: ¿Dije lo que pensaba o callé para evitar el conflicto? | T20: Del temperamento al carácter | U20: 6. El flemático: su desafío personal | V20: Evita los conflictos a cualquier precio
A21: aud-08 | B21: Hoy haz algo que te saque de tu rutina habitual: un camino distinto, un plan nuevo, una propuesta a tu familia. | C21: Rompe la rutina hoy | D21: fortaleza | E21: audacia | F21: voluntad | G21: familia | H21: accion | I21: =ROUND(AVERAGE(M21:P21),0) -> 3 | J21: 30 | K21: no | M21: 1 | N21: 3 | O21: 1 | P21: 5 | Q21: conformismo | R21: sí | S21: ¿Salí del statu quo por decisión propia? | T21: Del temperamento al carácter | U21: 6. El flemático: su desafío personal | V21: le gusta el statu quo, la seguridad, la rutina
A22: aud-09 | B22: Anima hoy a alguien de tu entorno a asumir un riesgo que le conviene, y ofrécele tu apoyo concreto. | C22: Anima a otro a arriesgar | D22: fortaleza | E22: audacia | F22: voluntad | G22: trabajo | H22: accion | I22: =ROUND(AVERAGE(M22:P22),0) -> 3 | J22: 10 | K22: sí | L22: colaborador indeciso | M22: 2 | N22: 3 | O22: 2 | P22: 4 | R22: sí | S22: ¿Animé a alguien a arriesgar en vez de protegerle? | T22: Creado para la grandeza | U22: Pasos prácticos: Fortaleza | V22: ¿Animo a otros a correr riesgos?
A23: aud-10 | B23: Da hoy un paso visible hacia un sueño que tienes aparcado: una llamada, una inscripción, un primer borrador. | C23: Un paso hacia el sueño aparcado | D23: fortaleza | E23: audacia | F23: voluntad | G23: vida interior | H23: accion | I23: =ROUND(AVERAGE(M23:P23),0) -> 4 | J23: 20 | K23: no | M23: 2 | N23: 5 | O23: 3 | P23: 5 | Q23: impaciencia | R23: no | S23: ¿Di el paso? ¿Qué excusa estuvo a punto de impedirlo? | T23: Coaching con Juana de Arco | U23: 4ª sesión: Hazte un plan de crecimiento | V23: Aprende a soñar
A24: aud-11 | B24: Cuando te veas pensando «¿quién soy yo para…?», completa la frase con lo que harías si no tuvieras miedo y hazlo hoy en versión pequeña. | C24: Actúa pese al '¿quién soy yo?' | D24: fortaleza | E24: audacia | F24: voluntad | G24: vida interior | H24: accion | I24: =ROUND(AVERAGE(M24:P24),0) -> 3 | J24: 15 | K24: no | L24: momento de pusilanimidad | M24: 1 | N24: 5 | O24: 2 | P24: 5 | Q24: conformismo | R24: sí | S24: ¿Detecté el pensamiento y actué a pesar de él? | T24: Coaching con Juana de Arco | U24: 3ª sesión: Humildad y magnanimidad | V24: Identifica los momentos de tu vida en los que te paralizaste por la modestia
A25: res-01 | B25: Termina hoy la tarea que tienes a medias antes de empezar ninguna nueva, cuidando los detalles finales. | C25: Termina lo que tienes a medias | D25: fortaleza | E25: resistencia | F25: voluntad | G25: trabajo | H25: accion | I25: =ROUND(AVERAGE(M25:P25),0) -> 3 | J25: 45 | K25: no | L25: tarea empezada y abandonada | M25: 2 | N25: 2 | O25: 5 | P25: 2 | R25: sí | S25: ¿La terminé del todo, con los detalles, o la dejé 'casi'? | T25: Del temperamento al carácter | U25: 7. Desarrolla la resistencia | V25: Termina el trabajo que te ocupa actualmente, cuidando los detalles
A26: res-02 | B26: Haz hoy primero lo importante y deja lo agradable para después, aunque lo agradable sea más urgente en apariencia. | C26: Lo importante antes que lo agradable | D26: fortaleza | E26: resistencia | F26: voluntad | G26: trabajo | H26: accion | I26: =ROUND(AVERAGE(M26:P26),0) -> 3 | J26: 60 | K26: no | L26: inicio de la jornada | M26: 2 | N26: 3 | O26: 5 | P26: 3 | R26: sí | S26: ¿Empecé por lo importante o por lo que me apetecía? | T26: Del temperamento al carácter | U26: 7. Desarrolla la resistencia | V26: Haz primero lo que es importante, y, lo que es agradable, hazlo después
A27: res-03 | B27: Sonríe hoy a alguien aunque no tengas ganas, y mantén el buen humor ante la primera contrariedad del día. | C27: Sonríe sin ganas | D27: fortaleza | E27: resistencia | F27: voluntad | G27: familia | H27: accion | I27: =ROUND(AVERAGE(M27:P27),0) -> 3 | J27: 1 | K27: sí | L27: mal humor matinal | M27: 3 | N27: 5 | O27: 2 | P27: 2 | R27: sí | S27: ¿Sonreí y mantuve el humor ante la contrariedad? | T27: Del temperamento al carácter | U27: 7. Desarrolla la resistencia | V27: Sonríe aunque no tengas ninguna gana
A28: res-04 | B28: Sé especialmente amable hoy con la persona que más te carga o te irrita. | C28: Amable con quien te irrita | D28: fortaleza | E28: resistencia | F28: voluntad | G28: trabajo | H28: accion | I28: =ROUND(AVERAGE(M28:P28),0) -> 3 | J28: 5 | K28: sí | L28: encuentro con persona difícil | M28: 4 | N28: 4 | O28: 3 | P28: 2 | Q28: falta de realismo | R28: sí | S28: ¿Fui amable de verdad o solo correcto? ¿Qué me costó más? | T28: Del temperamento al carácter | U28: 7. Desarrolla la resistencia | V28: Sé amable con los que te cargan
A29: res-05 | B29: Si hoy te llega una crítica o un comentario sobre ti, tómatelo con humor y no te defiendas. | C29: Ríete de lo que digan de ti | D29: fortaleza | E29: resistencia | F29: voluntad | G29: amistad | H29: omision | I29: =ROUND(AVERAGE(M29:P29),0) -> 4 | J29: 1 | K29: sí | L29: crítica recibida | M29: 4 | N29: 5 | O29: 3 | P29: 2 | R29: sí | S29: ¿Me reí o me defendí? ¿Cuánto duró el escozor? | T29: Del temperamento al carácter | U29: 7. Desarrolla la resistencia | V29: Acostúmbrate a tomarte en broma lo que otros dicen de ti
A30: res-06 | B30: Juega o dedica tiempo de verdad a tus hijos (o a alguien de tu familia) hoy, aunque llegues agotado. | C30: Juega aunque estés agotado | D30: fortaleza | E30: resistencia | F30: voluntad | G30: familia | H30: accion | I30: =ROUND(AVERAGE(M30:P30),0) -> 3 | J30: 20 | K30: sí | L30: llegada a casa cansado | M30: 3 | N30: 3 | O30: 3 | P30: 2 | R30: sí | S30: ¿Les dediqué tiempo real, sin móvil, a pesar del cansancio? | T30: Del temperamento al carácter | U30: 7. Desarrolla la resistencia | V30: Juega con tus hijos aunque estés muerto de cansancio
A31: res-07 | B31: Come hoy lo que te sirvan, sin quejas ni caprichos, y no comentes lo que no te gusta. | C31: Come sin caprichos | D31: fortaleza | E31: resistencia | F31: voluntad | G31: cuerpo | H31: omision | I31: =ROUND(AVERAGE(M31:P31),0) -> 3 | J31: 1 | K31: no | L31: comida en casa o fuera | M31: 2 | N31: 3 | O31: 4 | P31: 1 | R31: sí | S31: ¿Comí lo servido sin comentar ni rechazar? | T31: Del temperamento al carácter | U31: 7. Desarrolla la resistencia | V31: Come lo que te sirvan, sin caprichos
A32: res-08 | B32: Corrige hoy a alguien a tu cargo sobre algo que llevas tiempo dejando pasar, con caridad y sin rodeos. | C32: Corrige lo que llevas callando | D32: fortaleza | E32: resistencia | F32: voluntad | G32: trabajo | H32: accion | I32: =ROUND(AVERAGE(M32:P32),0) -> 4 | J32: 10 | K32: sí | L32: error repetido de un colaborador | M32: 2 | N32: 3 | O32: 5 | P32: 5 | Q32: conformismo | R32: no | S32: ¿Corregí con claridad y con afecto? ¿Qué me frenaba? | T32: Del temperamento al carácter | U32: 7. Desarrolla la resistencia | V32: Corrige a tus subordinados (con caridad), incluso si te cuesta
A33: res-09 | B33: Soporta hoy con buen humor una contrariedad concreta (retraso, cambio de planes, fallo técnico) sin quejarte en voz alta. | C33: Contrariedad sin queja | D33: fortaleza | E33: resistencia | F33: voluntad | G33: trabajo | H33: omision | I33: =ROUND(AVERAGE(M33:P33),0) -> 3 | J33: 1 | K33: no | L33: imprevisto | M33: 4 | N33: 4 | O33: 3 | P33: 1 | R33: sí | S33: ¿Me quejé en voz alta? ¿Cuántas veces? | T33: Del temperamento al carácter | U33: 7. Desarrolla la resistencia | V33: Soporta con buen humor las contrariedades, grandes y pequeñas
A34: res-10 | B34: Retoma hoy un proyecto personal que abandonaste y trabaja en él 25 minutos sin interrupciones. | C34: Retoma el proyecto abandonado | D34: fortaleza | E34: resistencia | F34: voluntad | G34: vida interior | H34: accion | I34: =ROUND(AVERAGE(M34:P34),0) -> 3 | J34: 25 | K34: no | M34: 2 | N34: 2 | O34: 5 | P34: 3 | R34: sí | S34: ¿Trabajé los 25 minutos completos? | T34: Del temperamento al carácter | U34: 5. El sanguíneo: su desafío personal | V34: Debe esforzarse por poner la última piedra en cada uno de sus proyectos
A35: res-11 | B35: Cumple hoy una promesa pequeña que hiciste y que te tienta no cumplir (una llamada, un favor, una hora acordada). | C35: Cumple la promesa pequeña | D35: fortaleza | E35: resistencia | F35: voluntad | G35: amistad | H35: accion | I35: =ROUND(AVERAGE(M35:P35),0) -> 3 | J35: 15 | K35: sí | L35: compromiso adquirido | M35: 2 | N35: 2 | O35: 5 | P35: 2 | R35: sí | S35: ¿Cumplí exactamente lo prometido y a tiempo? | T35: Del temperamento al carácter | U35: 5. El sanguíneo: su desafío personal | V35: Ha de practicar las virtudes de la resistencia y la fidelidad
A36: res-12 | B36: Mantén hoy una decisión ya tomada aunque surja oposición, sin reabrirla por comodidad. | C36: Mantén la decisión ante oposición | D36: fortaleza | E36: resistencia | F36: voluntad | G36: trabajo | H36: omision | I36: =ROUND(AVERAGE(M36:P36),0) -> 4 | J36: 5 | K36: sí | L36: crítica a una decisión | M36: 2 | N36: 4 | O36: 5 | P36: 4 | Q36: conformismo | R36: sí | S36: ¿Mantuve el rumbo o cedí para evitar fricción? | T36: Creado para la grandeza | U36: Pasos prácticos: Prudencia | V36: ¿Continúo fiel a mis decisiones sin importarme lo difícil que sea el camino?
A37: res-13 | B37: Defiende hoy la reputación de alguien ausente si oyes que se le critica injustamente. | C37: Defiende al ausente | D37: fortaleza | E37: resistencia | F37: voluntad | G37: trabajo | H37: accion | I37: =ROUND(AVERAGE(M37:P37),0) -> 4 | J37: 2 | K37: sí | L37: crítica a un ausente | M37: 2 | N37: 3 | O37: 4 | P37: 5 | Q37: conformismo | R37: sí | S37: ¿Salí en su defensa o callé para no incomodar? | T37: Creado para la grandeza | U37: Pasos prácticos: Fortaleza | V37: ¿Defiendo la reputación de quienes son víctima de rumores maliciosos?
A38: res-14 | B38: Dedica hoy un rato a una tarea tediosa pero necesaria que llevas evitando, y hazla bien hasta el final. | C38: La tarea tediosa, hasta el final | D38: fortaleza | E38: resistencia | F38: voluntad | G38: trabajo | H38: accion | I38: =ROUND(AVERAGE(M38:P38),0) -> 3 | J38: 30 | K38: no | M38: 2 | N38: 3 | O38: 5 | P38: 2 | R38: sí | S38: ¿La terminé con cuidado o la despaché deprisa? | T38: Liderazgo virtuoso | U38: Capítulo 4: Justicia y deberes ordinarios | V38: Los líderes buscan la perfección en su trabajo
A39: res-15 | B39: Vive cada hora de hoy como un capítulo nuevo: si fallas en algo por la mañana, empieza de cero por la tarde sin arrastrar el desánimo. | C39: Empieza de cero tras fallar | D39: fortaleza | E39: resistencia | F39: voluntad | G39: vida interior | H39: contemplacion | I39: =ROUND(AVERAGE(M39:P39),0) -> 3 | J39: 2 | K39: no | L39: fallo o error propio | M39: 3 | N39: 5 | O39: 2 | P39: 3 | Q39: perfeccionismo | R39: sí | S39: Tras un fallo, ¿me levanté rápido o me quedé en el desánimo? | T39: Liderazgo virtuoso | U39: Capítulo 2: Un programa para ganar | V39: Debemos considerar cada día, cada hora, como un nuevo capítulo de nuestra vida
A40: dom-01 | B40: Si hoy te contradicen, cuenta hasta diez antes de responder y hazlo en un tono más bajo del que te pide el cuerpo. | C40: Diez segundos antes de responder | D40: dominio de sí | F40: voluntad | G40: trabajo | H40: omision | I40: =ROUND(AVERAGE(M40:P40),0) -> 3 | J40: 1 | K40: sí | L40: opinión contraria a la tuya | M40: 5 | N40: 3 | O40: 2 | P40: 1 | R40: sí | S40: ¿Conté y bajé el tono? ¿La primera reacción fue física o decidí reaccionar así? | T40: Del temperamento al carácter | U40: 3. El colérico: su desafío personal | V40: no interpretar la opinión del otro como una declaración de guerra
A41: dom-02 | B41: Hoy no uses lenguaje vulgar ni alces la voz, pase lo que pase. | C41: Ni gritos ni palabrotas | D41: dominio de sí | F41: voluntad | G41: familia | H41: omision | I41: =ROUND(AVERAGE(M41:P41),0) -> 3 | J41: 1 | K41: sí | M41: 5 | N41: 2 | O41: 3 | P41: 1 | R41: sí | S41: ¿Alcé la voz o usé lenguaje vulgar? ¿En qué momento? | T41: Creado para la grandeza | U41: Pasos prácticos: Templanza | V41: ¿Reacciono con calma y cortesía a la crítica, sin alzar la voz ni usar lenguaje vulgar?
A42: dom-03 | B42: Elige una comodidad pequeña a la que renunciar hoy (azúcar, redes sociales, la siesta, el ascensor) y cúmplelo. | C42: Renuncia a una comodidad | D42: dominio de sí | F42: voluntad | G42: cuerpo | H42: omision | I42: =ROUND(AVERAGE(M42:P42),0) -> 3 | J42: 1 | K42: no | M42: 2 | N42: 3 | O42: 5 | P42: 3 | R42: sí | S42: ¿Cumplí la renuncia todo el día? | T42: Liderazgo virtuoso | U42: Capítulo 3: Dominio de sí | V42: aprender a decir que no a todo lo que es perjudicial o constituye una pérdida de tiempo
A43: dom-04 | B43: Hoy, cuando algo brillante te tiente (compra, novedad, notificación), espera una hora antes de atenderlo. | C43: Espera una hora ante lo brillante | D43: dominio de sí | F43: voluntad | G43: cuerpo | H43: omision | I43: =ROUND(AVERAGE(M43:P43),0) -> 3 | J43: 60 | K43: no | L43: impulso de compra o novedad | M43: 2 | N43: 2 | O43: 5 | P43: 2 | R43: sí | S43: ¿Esperé la hora? ¿Seguía queriéndolo después? | T43: Del temperamento al carácter | U43: 5. El sanguíneo: su desafío personal | V43: le atrae, como la urraca, todo lo que brilla
A44: dom-05 | B44: Hoy haz lo que deberías en lugar de lo que te apetece en al menos un momento concreto, y anótalo. | C44: Lo que debo, no lo que me apetece | D44: dominio de sí | F44: voluntad | G44: trabajo | H44: accion | I44: =ROUND(AVERAGE(M44:P44),0) -> 4 | J44: 15 | K44: no | M44: 3 | N44: 3 | O44: 5 | P44: 3 | R44: sí | S44: ¿En qué momento elegí el deber sobre el gusto? | T44: Creado para la grandeza | U44: Pasos prácticos: Templanza | V44: ¿Hago lo que «me gusta» hacer, o más bien lo que «debería»?
A45: dom-06 | B45: Revisa hoy tu consumo de pantallas e información: elimina una fuente que solo satisface curiosidad y no te hace mejor. | C45: Elimina una fuente de ruido | D45: dominio de sí | F45: voluntad | G45: cultura | H45: accion | I45: =ROUND(AVERAGE(M45:P45),0) -> 4 | J45: 10 | K45: no | M45: 3 | N45: 3 | O45: 5 | P45: 3 | R45: no | S45: ¿Qué fuente eliminé? ¿Qué sentí al hacerlo? | T45: Liderazgo virtuoso | U45: Capítulo 3: Studiositas frente a curiositas | V45: Los líderes son estudiosos, no curiosos
A46: dom-07 | B46: Cuando sientas envidia hoy por el éxito de alguien, dale las gracias o felicítale de forma concreta. | C46: Convierte la envidia en gratitud | D46: dominio de sí | F46: voluntad | G46: amistad | H46: accion | I46: =ROUND(AVERAGE(M46:P46),0) -> 3 | J46: 2 | K46: sí | L46: éxito ajeno | M46: 4 | N46: 4 | O46: 3 | P46: 2 | R46: sí | S46: ¿Felicité de verdad? ¿Qué sentí al hacerlo? | T46: Liderazgo virtuoso | U46: Capítulo 3: Gratitud frente a envidia | V46: Los líderes practican la virtud de la gratitud, que es opuesta a la envidia
A47: dom-08 | B47: Cuando hoy te invada la tristeza o la ansiedad, di en voz baja «esto no es tan grave como parece» y haz la siguiente tarea. | C47: Nombra la ansiedad y sigue | D47: dominio de sí | F47: voluntad | G47: vida interior | H47: accion | I47: =ROUND(AVERAGE(M47:P47),0) -> 3 | J47: 2 | K47: no | L47: bajón emocional | M47: 2 | N47: 5 | O47: 3 | P47: 2 | R47: sí | S47: ¿Lo hice? ¿Pude seguir trabajando? | T47: Del temperamento al carácter | U47: 4. El melancólico: su desafío personal | V47: El pesimismo y la ansiedad pueden vencerse por medio del realismo
A48: dom-09 | B48: Hoy no critiques a nadie que no esté presente, ni siquiera en tu cabeza. Si lo haces, para y piensa algo bueno de esa persona. | C48: Cero críticas al ausente | D48: dominio de sí | F48: voluntad | G48: trabajo | H48: omision | I48: =ROUND(AVERAGE(M48:P48),0) -> 3 | J48: 1 | K48: no | M48: 3 | N48: 5 | O48: 3 | P48: 2 | R48: sí | S48: ¿Cuántas veces critiqué a un ausente, aunque fuera mentalmente? | T48: Del temperamento al carácter | U48: 4. El melancólico: su desafío personal | V48: Tiene tendencia a criticar a sus colegas (aunque solo sea internamente)
A49: dom-10 | B49: Perdona hoy una ofensa concreta que guardas y hazlo visible: un saludo, un mensaje, un gesto normal con esa persona. | C49: Suelta una ofensa guardada | D49: dominio de sí | F49: voluntad | G49: amistad | H49: accion | I49: =ROUND(AVERAGE(M49:P49),0) -> 3 | J49: 5 | K49: sí | L49: persona con la que tienes rencor | M49: 3 | N49: 5 | O49: 2 | P49: 2 | R49: no | S49: ¿Hice el gesto? ¿Qué me costó más, la decisión o la ejecución? | T49: Del temperamento al carácter | U49: 4. El melancólico: su desafío personal | V49: le cuesta olvidar las ofensas sufridas
A50: dom-11 | B50: Agradece hoy en voz alta la ayuda de tres personas distintas, nombrando qué hicieron. | C50: Agradece tres veces | D50: dominio de sí | F50: voluntad | G50: trabajo | H50: accion | I50: =ROUND(AVERAGE(M50:P50),0) -> 3 | J50: 3 | K50: sí | M50: 4 | N50: 3 | O50: 1 | P50: 2 | R50: sí | S50: ¿A quién agradecí y por qué concreto? | T50: Liderazgo virtuoso | U50: Capítulo 3: Gratitud frente a envidia | V50: Dan las gracias y recompensan a las personas por sus esfuerzos
A51: dom-12 | B51: Elige hoy una pasión noble que tienes dormida (una causa, un proyecto de servicio, un arte) y dedícale 20 minutos. | C51: Despierta una pasión noble | D51: dominio de sí | F51: voluntad | G51: cultura | H51: accion | I51: =ROUND(AVERAGE(M51:P51),0) -> 3 | J51: 20 | K51: no | M51: 1 | N51: 2 | O51: 2 | P51: 5 | Q51: conformismo | R51: sí | S51: ¿Le dediqué el tiempo? ¿Qué se despertó? | T51: Del temperamento al carácter | U51: 6. El flemático: su desafío personal | V51: Debe estimular sus pasiones nobles
A52: dom-13 | B52: Detecta hoy en qué momento actúas por el placer de actuar y para hoy cinco minutos a preguntarte para qué lo haces. | C52: Para y pregunta para qué | D52: dominio de sí | F52: voluntad | G52: trabajo | H52: contemplacion | I52: =ROUND(AVERAGE(M52:P52),0) -> 3 | J52: 5 | K52: no | L52: jornada muy cargada | M52: 5 | N52: 1 | O52: 3 | P52: 1 | R52: sí | S52: ¿Paré? ¿Encontré el 'para qué' o seguí por inercia? | T52: Del temperamento al carácter | U52: 3. El colérico: su desafío personal | V52: Son muchos los coléricos que actúan por el placer de actuar
A53: dom-14 | B53: Hoy guarda un pequeño silencio cuando tengas ganas de opinar sobre algo que no te incumbe. | C53: Calla cuando no te incumbe | D53: dominio de sí | F53: voluntad | G53: trabajo | H53: omision | I53: =ROUND(AVERAGE(M53:P53),0) -> 3 | J53: 1 | K53: sí | M53: 5 | N53: 3 | O53: 4 | P53: 1 | R53: sí | S53: ¿Callé? ¿Cuántas veces estuve a punto de intervenir? | T53: Del temperamento al carácter | U53: 3. El colérico: su desafío personal | V53: debe aprender a controlar su lengua
A54: dom-15 | B54: Mantén hoy la paz en una situación que normalmente te pone a prueba, y hazlo sin fingir indiferencia. | C54: Paz en la prueba, sin fingir | D54: dominio de sí | F54: voluntad | G54: familia | H54: accion | I54: =ROUND(AVERAGE(M54:P54),0) -> 3 | J54: 5 | K54: sí | L54: situación tensa habitual | M54: 5 | N54: 4 | O54: 3 | P54: 1 | R54: sí | S54: ¿Mantuve la paz? ¿Fue paz real o frialdad? | T54: Creado para la grandeza | U54: Pasos prácticos: Templanza | V54: ¿Mantengo la paz incluso en aquellas circunstancias que me ponen a prueba?
A55: jus-01 | B55: Haz hoy tu trabajo ordinario con un nivel de cuidado superior al habitual en una tarea concreta, como un acto de servicio a quien la recibe. | C55: Trabaja hoy como servicio | D55: justicia | F55: voluntad | G55: trabajo | H55: accion | I55: =ROUND(AVERAGE(M55:P55),0) -> 3 | J55: 60 | K55: no | M55: 2 | N55: 3 | O55: 4 | P55: 2 | R55: sí | S55: ¿Trabajé mejor hoy en esa tarea? ¿Pensé en quién la recibe? | T55: Creado para la grandeza | U55: Pasos prácticos: Justicia | V55: ¿Entiendo el trabajo como un acto de servicio a todos?
A56: jus-02 | B56: Dedica hoy a tu familia un tiempo fijo y protegido, sin trabajo ni móvil, aunque haya tareas pendientes. | C56: Tiempo protegido para la familia | D56: justicia | F56: voluntad | G56: familia | H56: accion | I56: =ROUND(AVERAGE(M56:P56),0) -> 3 | J56: 60 | K56: sí | L56: tarde o noche | M56: 5 | N56: 3 | O56: 2 | P56: 2 | R56: sí | S56: ¿Respeté el tiempo? ¿Cuántas veces pensé en el trabajo? | T56: Creado para la grandeza | U56: Pasos prácticos: Justicia | V56: ¿Soy consciente de la diferencia entre el amor al trabajo y la adicción a éste?
A57: jus-03 | B57: Identifica hoy una pequeña incoherencia entre lo que muestras y lo que eres, y corrígela en una conversación. | C57: Cierra una incoherencia | D57: justicia | F57: voluntad | G57: vida interior | H57: accion | I57: =ROUND(AVERAGE(M57:P57),0) -> 4 | J57: 10 | K57: sí | M57: 3 | N57: 3 | O57: 5 | P57: 3 | R57: no | S57: ¿Qué incoherencia corregí? ¿Cómo reaccionó la otra persona? | T57: Creado para la grandeza | U57: Pasos prácticos: Justicia | V57: ¿Hay en mí algún tipo de dicotomía entre mi yo interior y el rostro que muestro?
A58: jus-04 | B58: Di hoy una verdad moral que crees aunque sea impopular en tu entorno, con respeto y sin agresividad. | C58: Di la verdad impopular | D58: justicia | F58: voluntad | G58: trabajo | H58: accion | I58: =ROUND(AVERAGE(M58:P58),0) -> 4 | J58: 5 | K58: sí | L58: conversación sobre tema delicado | M58: 2 | N58: 4 | O58: 4 | P58: 5 | Q58: conformismo | R58: no | S58: ¿La dije? ¿Con respeto? ¿Qué temía perder? | T58: Creado para la grandeza | U58: Pasos prácticos: Justicia | V58: ¿Defiendo la verdad moral, incluso si ello implica contradecir lo políticamente correcto?
A59: jus-05 | B59: Pregunta hoy a una persona a tu cargo cómo está, de verdad, y escucha cinco minutos sin hablar de trabajo. | C59: Pregunta cómo está, y escucha | D59: justicia | F59: voluntad | G59: trabajo | H59: accion | I59: =ROUND(AVERAGE(M59:P59),0) -> 3 | J59: 10 | K59: sí | L59: encuentro con colaborador | M59: 5 | N59: 4 | O59: 1 | P59: 2 | R59: sí | S59: ¿Pregunté y escuché sin desviar al trabajo? | T59: Creado para la grandeza | U59: Pasos prácticos: Humildad | V59: ¿Me preocupo de que aquellos que trabajan para mí y conmigo sean felices?
A60: jus-06 | B60: Trabaja hoy en equipo en algo que preferirías hacer a tu manera, y acepta la forma del grupo. | C60: Hazlo a la manera del equipo | D60: justicia | F60: voluntad | G60: trabajo | H60: accion | I60: =ROUND(AVERAGE(M60:P60),0) -> 3 | J60: 30 | K60: sí | L60: tarea compartida | M60: 4 | N60: 5 | O60: 2 | P60: 1 | R60: sí | S60: ¿Acepté la forma del grupo o la saboteé en silencio? | T60: Del temperamento al carácter | U60: 4. El melancólico: su desafío personal | V60: Debe aprender a trabajar en equipo (le encanta hacer las cosas a su manera)
A61: jus-07 | B61: Si hoy el grupo decide algo contra tu opinión, súmate con entusiasmo a ejecutarlo y no digas «te lo dije» si falla. | C61: Súmate a la decisión del grupo | D61: justicia | F61: voluntad | G61: trabajo | H61: omision | I61: =ROUND(AVERAGE(M61:P61),0) -> 3 | J61: 5 | K61: sí | L61: decisión colectiva contraria | M61: 5 | N61: 4 | O61: 2 | P61: 1 | R61: sí | S61: ¿Participé con entusiasmo? ¿Evité el 'te lo dije'? | T61: Creado para la grandeza | U61: Pasos prácticos: Humildad | V61: ¿Participo con entusiasmo en la puesta en marcha de las decisiones a las que me opuse?
A62: jus-08 | B62: Cultiva hoy una amistad, no una relación: llama a un amigo sin ningún motivo práctico. | C62: Llama a un amigo sin motivo | D62: justicia | F62: voluntad | G62: amistad | H62: accion | I62: =ROUND(AVERAGE(M62:P62),0) -> 3 | J62: 15 | K62: sí | M62: 4 | N62: 4 | O62: 1 | P62: 3 | R62: sí | S62: ¿Llamé? ¿Hablamos de algo que importaba? | T62: Creado para la grandeza | U62: Pasos prácticos: Justicia | V62: ¿Cultivo la amistad o solo las relaciones?
A63: jus-09 | B63: Hoy trata a cada persona con la que hables como persona y no como recurso: usa su nombre y mírala al hablar. | C63: Nombre y mirada a cada persona | D63: justicia | F63: voluntad | G63: trabajo | H63: accion | I63: =ROUND(AVERAGE(M63:P63),0) -> 3 | J63: 1 | K63: sí | M63: 5 | N63: 3 | O63: 1 | P63: 2 | R63: sí | S63: ¿Hubo alguien a quien traté como un medio? | T63: Creado para la grandeza | U63: Pasos prácticos: Justicia | V63: ¿Soy consciente de que la gente son personas y no factores de producción abstractos?
A64: jus-10 | B64: Cumple hoy una obligación social o cívica que sueles posponer (una gestión, una respuesta debida, un compromiso con tu comunidad). | C64: Cumple la obligación pospuesta | D64: justicia | F64: voluntad | G64: sociedad | H64: accion | I64: =ROUND(AVERAGE(M64:P64),0) -> 3 | J64: 30 | K64: no | M64: 2 | N64: 3 | O64: 4 | P64: 2 | R64: sí | S64: ¿La cumplí hoy? | T64: Liderazgo virtuoso | U64: Capítulo 4: Justicia y bien común | V64: mediante el cumplimiento fiel de sus responsabilidades profesionales, sociales, familiares y religiosas
A65: jus-11 | B65: Contribuye hoy activamente a algo común que no te beneficia directamente (una tarea de equipo, un favor a un vecino, una iniciativa del barrio). | C65: Aporta al bien común sin beneficio | D65: justicia | F65: voluntad | G65: sociedad | H65: accion | I65: =ROUND(AVERAGE(M65:P65),0) -> 3 | J65: 30 | K65: sí | M65: 1 | N65: 3 | O65: 2 | P65: 5 | Q65: conformismo | R65: sí | S65: ¿Lo hice? ¿Esperé reconocimiento? | T65: Del temperamento al carácter | U65: 6. El flemático: su desafío personal | V65: para construir el bien común, debe aprender a vencer su apatía
A66: jus-12 | B66: Repara hoy un pequeño daño que hayas causado (un retraso, una palabra de más, un olvido) pidiendo disculpas sin justificarte. | C66: Repara sin justificarte | D66: justicia | F66: voluntad | G66: familia | H66: accion | I66: =ROUND(AVERAGE(M66:P66),0) -> 3 | J66: 5 | K66: sí | L66: daño causado | M66: 5 | N66: 2 | O66: 3 | P66: 2 | R66: sí | S66: ¿Pedí disculpas sin añadir un 'pero'? | T66: Del temperamento al carácter | U66: 3. El colérico: su desafío personal | V66: No reconoce fácilmente sus errores
A67: jus-13 | B67: Ayuda hoy a alguien a darse cuenta de un defecto suyo, con afecto y pensando en su bien, no en tu comodidad. | C67: Ayúdale a ver su defecto | D67: justicia | F67: voluntad | G67: amistad | H67: accion | I67: =ROUND(AVERAGE(M67:P67),0) -> 4 | J67: 10 | K67: sí | L67: persona cercana con un defecto visible | M67: 2 | N67: 3 | O67: 4 | P67: 5 | Q67: conformismo | R67: no | S67: ¿Se lo dije con afecto? ¿Cómo lo recibió? | T67: Liderazgo virtuoso | U67: Capítulo 2: Un programa para ganar | V67: practicar la justicia significará ayudarles a darse cuenta de sus defectos
A68: jus-14 | B68: Da hoy a alguien el reconocimiento que le debes y que llevas tiempo sin expresar. | C68: Reconoce lo que debes | D68: justicia | F68: voluntad | G68: trabajo | H68: accion | I68: =ROUND(AVERAGE(M68:P68),0) -> 3 | J68: 5 | K68: sí | M68: 4 | N68: 3 | O68: 1 | P68: 2 | R68: sí | S68: ¿A quién reconocí? ¿Fue específico? | T68: Liderazgo virtuoso | U68: Capítulo 4: Justicia | V68: La justicia es el hábito de dar a cada uno lo suyo
A69: mag-01 | B69: Escribe hoy tres cosas que se te dan especialmente bien y pregunta a un amigo si está de acuerdo. | C69: Nombra tu talento y contrástalo | D69: magnanimidad | F69: corazon | G69: vida interior | H69: accion | I69: =ROUND(AVERAGE(M69:P69),0) -> 3 | J69: 15 | K69: sí | M69: 2 | N69: 2 | O69: 3 | P69: 5 | R69: no | S69: ¿Las escribí? ¿Qué dijo el amigo? | T69: Creado para la grandeza | U69: Pasos prácticos: Magnanimidad | V69: ¿He pedido alguna vez a mis amigos que me ayuden a descubrir en qué soy bueno?
A70: mag-02 | B70: Dedica hoy 15 minutos a contemplar algo bello (música, un cuadro, un paisaje, un texto) sin hacer nada más. | C70: Quince minutos de belleza | D70: magnanimidad | F70: corazon | G70: cultura | H70: contemplacion | I70: =ROUND(AVERAGE(M70:P70),0) -> 3 | J70: 15 | K70: no | M70: 5 | N70: 1 | O70: 3 | P70: 4 | R70: sí | S70: ¿Lo hice sin interrupciones? ¿Qué provocó en mí? | T70: Del temperamento al carácter | U70: 7. Desarrolla la magnanimidad | V70: Aprende a contemplar la belleza, a maravillarte
A71: mag-03 | B71: Identifica hoy a una persona magnánima que admiras y escríbele o búscala para quedar. | C71: Busca la compañía de un magnánimo | D71: magnanimidad | F71: corazon | G71: amistad | H71: accion | I71: =ROUND(AVERAGE(M71:P71),0) -> 3 | J71: 10 | K71: sí | M71: 2 | N71: 3 | O71: 2 | P71: 5 | R71: no | S71: ¿Di el paso de contactar? | T71: Del temperamento al carácter | U71: 7. Desarrolla la magnanimidad | V71: Identifica a qué personas magnánimas te gustaría ver este año y busca su compañía
A72: mag-04 | B72: Revisa hoy tu «ambiente»: elimina una lectura, serie o cuenta que te empequeñece y sustitúyela por algo noble. | C72: Limpia tu ambiente | D72: magnanimidad | F72: corazon | G72: cultura | H72: accion | I72: =ROUND(AVERAGE(M72:P72),0) -> 3 | J72: 15 | K72: no | M72: 3 | N72: 2 | O72: 5 | P72: 3 | R72: no | S72: ¿Qué quité y qué puse en su lugar? | T72: Del temperamento al carácter | U72: 7. Desarrolla la magnanimidad | V72: Crea en torno tuyo un «ambiente magnánimo»
A73: mag-05 | B73: Fija hoy un objetivo más alto de lo habitual para una tarea concreta y díselo a alguien. | C73: Sube el listón y dilo | D73: magnanimidad | F73: corazon | G73: trabajo | H73: accion | I73: =ROUND(AVERAGE(M73:P73),0) -> 3 | J73: 10 | K73: sí | L73: planificación del día | M73: 1 | N73: 3 | O73: 3 | P73: 5 | Q73: autosatisfacción | R73: sí | S73: ¿Fijé un objetivo alto? ¿Lo comuniqué? | T73: Creado para la grandeza | U73: Pasos prácticos: Magnanimidad | V73: ¿Establezco metas altas para mí y para los demás?
A74: mag-06 | B74: Dedica hoy 20 minutos a imaginar sin límites cómo sería tu vida o tu trabajo dentro de diez años si cumplieras tu misión. Escríbelo. | C74: Imagina a diez años | D74: magnanimidad | F74: corazon | G74: vida interior | H74: contemplacion | I74: =ROUND(AVERAGE(M74:P74),0) -> 3 | J74: 20 | K74: no | M74: 3 | N74: 1 | O74: 3 | P74: 5 | Q74: conformismo | R74: no | S74: ¿Lo escribí? ¿Me atreví a imaginar en grande? | T74: Del temperamento al carácter | U74: 7. Desarrolla la magnanimidad | V74: Dedica tiempo a tu imaginación. Trabájala, enriquécela, llévala hasta el límite
A75: mag-07 | B75: Hoy no te compares con nadie. Cada vez que lo hagas, sustituye la comparación por una pregunta: «¿qué puedo hacer yo con mi talento?». | C75: Cero comparaciones hoy | D75: magnanimidad | F75: corazon | G75: vida interior | H75: omision | I75: =ROUND(AVERAGE(M75:P75),0) -> 4 | J75: 1 | K75: no | M75: 3 | N75: 4 | O75: 4 | P75: 3 | R75: sí | S75: ¿Cuántas veces me comparé? ¿Logré sustituirlo? | T75: Del temperamento al carácter | U75: 7. Desarrolla la magnanimidad | V75: No te compares con nadie
A76: mag-08 | B76: No dejes pasar hoy una ocasión de hacer un bien concreto por miedo o pereza, por pequeño que sea. | C76: No dejes pasar la ocasión | D76: magnanimidad | F76: corazon | G76: sociedad | H76: accion | I76: =ROUND(AVERAGE(M76:P76),0) -> 4 | J76: 10 | K76: sí | L76: ocasión de ayudar | M76: 2 | N76: 4 | O76: 3 | P76: 5 | Q76: conformismo | R76: sí | S76: ¿Hubo una ocasión que dejé pasar? ¿Por miedo o por pereza? | T76: Del temperamento al carácter | U76: 7. Desarrolla la magnanimidad | V76: No dejes pasar la ocasión de actuar
A77: mag-09 | B77: Busca hoy la grandeza en una tarea ordinaria (una comida, un informe, una clase) y hazla como si fuera lo más importante del día. | C77: Grandeza en lo ordinario | D77: magnanimidad | F77: corazon | G77: familia | H77: accion | I77: =ROUND(AVERAGE(M77:P77),0) -> 3 | J77: 30 | K77: no | M77: 3 | N77: 2 | O77: 3 | P77: 3 | R77: sí | S77: ¿En qué tarea busqué la grandeza? ¿Se notó? | T77: Del temperamento al carácter | U77: 7. Desarrolla la magnanimidad | V77: Busca la grandeza en la realidad inmediata y tangible
A78: mag-10 | B78: Pregúntate hoy: «¿en qué medida, cumpliendo la misión de mi organización, cumplo la mía?». Escribe la respuesta honesta. | C78: Tu misión y la de tu empresa | D78: magnanimidad | F78: corazon | G78: trabajo | H78: contemplacion | I78: =ROUND(AVERAGE(M78:P78),0) -> 3 | J78: 10 | K78: no | M78: 3 | N78: 3 | O78: 3 | P78: 4 | R78: no | S78: ¿Pude responder? ¿Qué me dice la respuesta? | T78: Del temperamento al carácter | U78: 7. Desarrolla la magnanimidad | V78: ¿En qué medida, cumpliendo la misión de mi empresa, estoy cumpliendo la mía propia?
A79: mag-11 | B79: Dedica hoy más energía a desarrollar un punto fuerte tuyo que a corregir un defecto: practica ese talento 30 minutos. | C79: Entrena tu punto fuerte | D79: magnanimidad | F79: corazon | G79: vida interior | H79: accion | I79: =ROUND(AVERAGE(M79:P79),0) -> 3 | J79: 30 | K79: no | M79: 3 | N79: 3 | O79: 3 | P79: 4 | R79: sí | S79: ¿Practiqué mi punto fuerte? ¿Cuál? | T79: Creado para la grandeza | U79: Pasos prácticos: Magnanimidad | V79: debería estar más preocupado en desarrollar y aumentar mis puntos fuertes
A80: mag-12 | B80: Inspira hoy a un colega o amigo un sentido de misión: pregúntale para qué hace lo que hace y escucha. | C80: Pregunta a otro por su misión | D80: magnanimidad | F80: corazon | G80: trabajo | H80: accion | I80: =ROUND(AVERAGE(M80:P80),0) -> 3 | J80: 15 | K80: sí | M80: 3 | N80: 4 | O80: 2 | P80: 4 | R80: sí | S80: ¿Tuvimos la conversación? ¿Qué descubrió? | T80: Creado para la grandeza | U80: Pasos prácticos: Magnanimidad | V80: ¿Trato de inspirar en mis amigos y colegas un sentido de misión?
A81: mag-13 | B81: Mira hoy un problema de tu entorno (trabajo, barrio, familia) como una cima a conquistar y no como una carga. Escribe el primer paso. | C81: El problema como cima | D81: magnanimidad | F81: corazon | G81: sociedad | H81: contemplacion | I81: =ROUND(AVERAGE(M81:P81),0) -> 4 | J81: 10 | K81: no | L81: problema que te desanima | M81: 2 | N81: 5 | O81: 3 | P81: 5 | R81: sí | S81: ¿Cambié la mirada? ¿Escribí el primer paso? | T81: Creado para la grandeza | U81: Pasos prácticos: Magnanimidad | V81: ¿Veo los obstáculos como cimas que conquistar o me rindo al pesimismo?
A82: mag-14 | B82: Escribe hoy tu historia personal en cinco líneas: las personas, los libros y los hechos que te han hecho quien eres. | C82: Tu historia en cinco líneas | D82: magnanimidad | F82: corazon | G82: vida interior | H82: contemplacion | I82: =ROUND(AVERAGE(M82:P82),0) -> 4 | J82: 20 | K82: no | M82: 4 | N82: 2 | O82: 4 | P82: 4 | R82: no | S82: ¿La escribí? ¿Qué tema principal apareció? | T82: Del temperamento al carácter | U82: 8. Descubre tu misión | V82: Tu historia debe ser dramática, poética, simbólica y corta
A83: mag-15 | B83: Lee hoy 20 minutos la biografía de una persona noble de la historia, en lugar de noticias o redes. | C83: Veinte minutos con un grande | D83: magnanimidad | F83: corazon | G83: cultura | H83: contemplacion | I83: =ROUND(AVERAGE(M83:P83),0) -> 3 | J83: 20 | K83: no | M83: 3 | N83: 2 | O83: 4 | P83: 3 | R83: sí | S83: ¿Leí? ¿Qué me quedo de esa persona? | T83: Coaching con Juana de Arco | U83: 4ª sesión: Hazte un plan de crecimiento | V83: Estudia las biografías de las personalidades nobles de la historia
A84: mag-16 | B84: Rechaza hoy la autosatisfacción: en algo que crees hacer «bastante bien», da un paso más. | C84: Un paso más donde ya haces 'bastante' | D84: magnanimidad | F84: corazon | G84: trabajo | H84: accion | I84: =ROUND(AVERAGE(M84:P84),0) -> 3 | J84: 15 | K84: no | M84: 3 | N84: 3 | O84: 3 | P84: 4 | Q84: autosatisfacción | R84: sí | S84: ¿Dónde di el paso extra? | T84: Liderazgo virtuoso | U84: Capítulo 2: Un programa para ganar | V84: Esta indulgencia con nosotros mismos es incompatible con la magnanimidad
A85: mag-17 | B85: Hoy haz algo que verdaderamente deseas en el fondo y que vienes negándote «por deber»: identifícalo y dale un primer espacio. | C85: Haz lo que de verdad deseas | D85: magnanimidad | F85: corazon | G85: vida interior | H85: accion | I85: =ROUND(AVERAGE(M85:P85),0) -> 3 | J85: 30 | K85: no | M85: 3 | N85: 4 | O85: 2 | P85: 4 | Q85: voluntarismo | R85: no | S85: ¿Lo identifiqué? ¿Le di espacio sin culpa? | T85: Corazón libre | U85: 4. El voluntarista espiritualista | V85: Aprende a hacer lo que verdaderamente deseas hacer. Aprende a ser feliz
A86: hum-01 | B86: Haz hoy tu examen de conciencia de tres minutos antes de dormir: qué hice bien, qué mal, y un propósito concreto para mañana. | C86: Examen de tres minutos | D86: humildad | E86: fundamental | F86: corazon | G86: vida interior | H86: contemplacion | I86: =ROUND(AVERAGE(M86:P86),0) -> 4 | J86: 3 | K86: no | L86: antes de dormir | M86: 4 | N86: 2 | O86: 5 | P86: 3 | R86: sí | S86: ¿Lo hice? ¿Salió un propósito concreto? | T86: Liderazgo virtuoso | U86: Capítulo 2: Examen de conciencia | V86: dedicar no más de tres minutos antes de acostarse a examinar nuestro comportamiento
A87: hum-02 | B87: Pide hoy a alguien de confianza que te diga un defecto tuyo que ve, y escúchalo sin defenderte ni explicarte. | C87: Pide un defecto y no te defiendas | D87: humildad | E87: fundamental | F87: corazon | G87: amistad | H87: accion | I87: =ROUND(AVERAGE(M87:P87),0) -> 4 | J87: 10 | K87: sí | M87: 5 | N87: 3 | O87: 4 | P87: 3 | R87: no | S87: ¿Pregunté? ¿Me defendí? | T87: Del temperamento al carácter | U87: 5. El sanguíneo: su desafío personal | V87: Conoce a los demás mejor de lo que se conoce a sí mismo
A88: hum-03 | B88: Reconoce hoy un error tuyo en voz alta delante de quienes lo vieron, sin minimizarlo. | C88: Reconoce el error en público | D88: humildad | E88: fundamental | F88: corazon | G88: trabajo | H88: accion | I88: =ROUND(AVERAGE(M88:P88),0) -> 3 | J88: 2 | K88: sí | L88: error visible | M88: 5 | N88: 3 | O88: 2 | P88: 3 | R88: sí | S88: ¿Lo reconocí? ¿Lo minimicé con un 'pero'? | T88: Del temperamento al carácter | U88: 3. El colérico: su desafío personal | V88: No reconoce fácilmente sus errores
A89: hum-04 | B89: Hoy, en una tarea de alguien a tu cargo, no intervengas ni la hagas por él aunque veas que podrías hacerla mejor. | C89: No hagas su trabajo | D89: humildad | E89: fraternal | F89: corazon | G89: trabajo | H89: omision | I89: =ROUND(AVERAGE(M89:P89),0) -> 3 | J89: 1 | K89: sí | L89: colaborador en una tarea | M89: 5 | N89: 4 | O89: 2 | P89: 2 | R89: sí | S89: ¿Me contuve? ¿Qué me costó más? | T89: Creado para la grandeza | U89: Pasos prácticos: Humildad | V89: ¿Evito la tentación de hacer el trabajo de mis subordinados en su lugar?
A90: hum-05 | B90: Delega hoy una decisión real (no solo una tarea) a alguien de tu equipo o de tu familia, y respeta lo que decida. | C90: Delega una decisión, no una tarea | D90: humildad | E90: fraternal | F90: corazon | G90: trabajo | H90: accion | I90: =ROUND(AVERAGE(M90:P90),0) -> 4 | J90: 10 | K90: sí | M90: 5 | N90: 4 | O90: 3 | P90: 2 | R90: sí | S90: ¿Delegué la decisión? ¿La respeté aunque no fuera la mía? | T90: Creado para la grandeza | U90: Pasos prácticos: Humildad | V90: ¿Sé delegar de buena gana el poder?
A91: hum-06 | B91: Enseña hoy en lugar de ordenar: cuando pidas algo, explica el porqué y pregunta si tiene sentido para la otra persona. | C91: Enseña, no ordenes | D91: humildad | E91: fraternal | F91: corazon | G91: familia | H91: accion | I91: =ROUND(AVERAGE(M91:P91),0) -> 3 | J91: 5 | K91: sí | L91: instrucción a alguien | M91: 5 | N91: 3 | O91: 2 | P91: 2 | R91: sí | S91: ¿Expliqué el porqué? ¿Pregunté? | T91: Del temperamento al carácter | U91: 7. Desarrolla la humildad | V91: enseña en lugar de ordenar, inspira en lugar de echar reprimendas
A92: hum-07 | B92: Haz hablar hoy en una reunión a la persona más callada, y pide al que más habla (quizá tú) que ceda. | C92: Da voz al callado | D92: humildad | E92: fraternal | F92: corazon | G92: trabajo | H92: accion | I92: =ROUND(AVERAGE(M92:P92),0) -> 3 | J92: 5 | K92: sí | L92: reunión de grupo | M92: 5 | N92: 2 | O92: 3 | P92: 2 | R92: sí | S92: ¿Lo hice? ¿Qué aportó el callado? | T92: Creado para la grandeza | U92: Pasos prácticos: Humildad | V92: ¿Hago hablar al reticente, animo al dominante a ceder?
A93: hum-08 | B93: Comparte hoy una información útil que estabas guardando para ti, con quien la necesita. | C93: Comparte lo que guardabas | D93: humildad | E93: fraternal | F93: corazon | G93: trabajo | H93: accion | I93: =ROUND(AVERAGE(M93:P93),0) -> 3 | J93: 5 | K93: sí | M93: 4 | N93: 4 | O93: 2 | P93: 2 | R93: sí | S93: ¿Qué compartí? ¿Por qué lo guardaba? | T93: Creado para la grandeza | U93: Pasos prácticos: Humildad | V93: ¿Comparto la información? ¿Evito hacerme a mí mismo indispensable?
A94: hum-09 | B94: Ayuda hoy a una persona a descubrir un talento suyo: díselo con un ejemplo concreto de cuándo lo viste. | C94: Señala el talento de otro | D94: humildad | E94: fraternal | F94: corazon | G94: familia | H94: accion | I94: =ROUND(AVERAGE(M94:P94),0) -> 3 | J94: 5 | K94: sí | M94: 4 | N94: 4 | O94: 2 | P94: 3 | R94: sí | S94: ¿A quién? ¿Qué talento? ¿Cómo reaccionó? | T94: Del temperamento al carácter | U94: 7. Desarrolla la humildad | V94: Ayúdales a descubrir sus talentos, a hacerlos rendir
A95: hum-10 | B95: Hoy sirve en algo pequeño y poco visible en casa o en el trabajo, sin que nadie lo sepa. | C95: Sirve en lo invisible | D95: humildad | E95: fraternal | F95: corazon | G95: familia | H95: accion | I95: =ROUND(AVERAGE(M95:P95),0) -> 3 | J95: 10 | K95: no | M95: 4 | N95: 4 | O95: 2 | P95: 2 | R95: sí | S95: ¿Qué hice? ¿Alguien lo supo? | T95: Liderazgo virtuoso | U95: Capítulo 1: Magnanimidad y humildad | V95: Un líder es siempre un servidor
A96: hum-11 | B96: Recuerda hoy, al empezar, que tu energía y tus talentos no son mérito tuyo sino un don. Dilo en una frase de agradecimiento. | C96: Tu fuerza es un don | D96: humildad | E96: fundamental | F96: corazon | G96: vida interior | H96: contemplacion | I96: =ROUND(AVERAGE(M96:P96),0) -> 3 | J96: 2 | K96: no | L96: inicio del día | M96: 5 | N96: 2 | O96: 3 | P96: 3 | R96: sí | S96: ¿Lo hice? ¿Cambió algo en cómo traté a los demás? | T96: Del temperamento al carácter | U96: 3. El colérico: su desafío personal | V96: debe comprender que su fuerza fisiológica no es resultado de un esfuerzo personal, sino un don
A97: hum-12 | B97: Hoy no humilles a nadie «por la causa»: si tienes que exigir, hazlo respetando los sentimientos y la libertad del otro. | C97: Exige sin humillar | D97: humildad | E97: fraternal | F97: corazon | G97: trabajo | H97: omision | I97: =ROUND(AVERAGE(M97:P97),0) -> 3 | J97: 1 | K97: sí | L97: presión por resultados | M97: 5 | N97: 2 | O97: 2 | P97: 1 | R97: sí | S97: ¿Herí a alguien en nombre del objetivo? | T97: Del temperamento al carácter | U97: 3. El colérico: su desafío personal | V97: no herir sus sentimientos, no violar su dignidad en nombre de una «causa sagrada»
A98: hum-13 | B98: Sal hoy de ti mismo: dedica 15 minutos a alguien que lo necesite, sin pensar en tus propios problemas mientras tanto. | C98: Quince minutos fuera de ti | D98: humildad | E98: fraternal | F98: corazon | G98: amistad | H98: accion | I98: =ROUND(AVERAGE(M98:P98),0) -> 3 | J98: 15 | K98: sí | M98: 3 | N98: 5 | O98: 2 | P98: 3 | R98: sí | S98: ¿Estuve presente de verdad o seguí dentro de mi cabeza? | T98: Del temperamento al carácter | U98: 4. El melancólico: su desafío personal | V98: le resulta difícil servir: está absorto en sí mismo
A99: hum-14 | B99: Distingue hoy en tu examen nocturno un fallo de temperamento (primera reacción) de un fallo de carácter (decisión). Anota uno de cada. | C99: Temperamento o carácter | D99: humildad | E99: fundamental | F99: corazon | G99: vida interior | H99: contemplacion | I99: =ROUND(AVERAGE(M99:P99),0) -> 3 | J99: 5 | K99: no | L99: antes de dormir | M99: 3 | N99: 2 | O99: 4 | P99: 3 | Q99: determinismo | R99: sí | S99: ¿Supe distinguirlos? ¿Me excusé con el temperamento? | T99: Liderazgo virtuoso | U99: Capítulo 2: Examen de conciencia | V99: Distinga entre sus defectos de carácter y sus defectos de temperamento
A100: hum-15 | B100: Pide hoy ayuda para algo que podrías hacer solo. | C100: Pide ayuda aunque puedas solo | D100: humildad | E100: fraternal | F100: corazon | G100: trabajo | H100: accion | I100: =ROUND(AVERAGE(M100:P100),0) -> 4 | J100: 5 | K100: sí | M100: 5 | N100: 4 | O100: 2 | P100: 3 | R100: sí | S100: ¿Pedí ayuda? ¿Qué sentí al hacerlo? | T100: Creado para la grandeza | U100: Pasos prácticos: Humildad | V100: ¿Requiero las aportaciones de los demás a la hora de solucionar mis problemas?
...

Sheet Catálogo
A1: Virtudes
A2: virtud | B2: subcomponentes | C2: facultad | D2: qué permite (Liderazgo virtuoso) | E2: fuente
A3: prudencia | B3: deliberacion / decision | C3: razon | D3: Tomar buenas decisiones | E3: Liderazgo virtuoso
A4: fortaleza | B4: audacia / resistencia | C4: voluntad | D4: Mantener el rumbo y resistir presiones | E4: Liderazgo virtuoso
A5: dominio de sí | B5: — | C5: voluntad | D5: Sujetar las pasiones al espíritu y dirigirlas a la misión | E5: Liderazgo virtuoso
A6: justicia | B6: comunión / bien común | C6: voluntad | D6: Dar a cada uno lo suyo y entrar en el corazón de los demás | E6: Liderazgo virtuoso
A7: magnanimidad | B7: contemplación / acción | C7: corazon | D7: Responder a la vocación, realizar la misión, fijar metas altas | E7: Liderazgo virtuoso
A8: humildad | B8: fundamental (conocimiento de sí) / fraternal (servicio) | C8: corazon | D8: Superar el ego y servir a los demás de manera habitual | E8: Liderazgo virtuoso
A11: Temperamentos
A12: temperamento | B12: orientación | C12: virtud-reto | D12: puntos débiles clave | E12: fuente
A13: colérico | B13: Acción | C13: humildad | D13: Orgullo e ira; decide sin deliberar; activismo ciego; no reconoce errores; le cuesta servir | E13: Del temperamento al carácter
A14: melancólico | B14: Idea | C14: audacia | D14: Teme la acción y el riesgo; pesimismo; se inquieta por nimiedades; crítica y susceptibilidad; mal en equipo | E14: Del temperamento al carácter
A15: sanguíneo | B15: Personas | C15: resistencia | D15: Inconstancia; empieza y no termina; superficialidad; controla mal los sentidos externos; quiere agradar | E15: Del temperamento al carácter
A16: flemático | B16: Paz | C16: magnanimidad | D16: Statu quo; evita conflictos; miedo a equivocarse; apatía; no sabe soñar | E16: Del temperamento al carácter
A19: Perfiles combinados (dominante-secundario)
A20: perfil | B20: temperamentos | C20: virtud-reto | D20: fuente
A21: Contemplativo | B21: melancólico | C21: audacia | D21: Grandir avec son tempérament
A22: Contemplativo activo | B22: melancólico-colérico | C22: humildad fraternal | D22: Grandir avec son tempérament
A23: Contemplativo pragmático | B23: melancólico-flemático | C23: audacia | D23: Grandir avec son tempérament
A24: Comunicador | B24: sanguíneo | C24: resistencia | D24: Grandir avec son tempérament
A25: Comunicador focalizado | B25: sanguíneo-colérico | C25: humildad fundamental | D25: Grandir avec son tempérament
A26: Comunicador discreto | B26: sanguíneo-flemático | C26: magnanimidad | D26: Grandir avec son tempérament
A27: Mediador | B27: flemático | C27: magnanimidad | D27: Grandir avec son tempérament
A28: Mediador contemplativo | B28: flemático-melancólico | C28: audacia | D28: Grandir avec son tempérament
A31: Ámbitos
A32: ámbito | B32: descripción
A33: trabajo | B33: Vida profesional, equipo, colaboradores, decisiones
A34: familia | B34: Pareja, hijos, hogar
A35: amistad | B35: Amigos, relaciones personales
A36: vida interior | B36: Conocimiento propio, misión, examen, oración o meditación
A37: cultura | B37: Lecturas, música, pantallas, belleza, ambiente
A38: cuerpo | B38: Comida, descanso, sentidos, comodidades
A39: sociedad | B39: Comunidad, bien común, obligaciones cívicas
A42: Obstáculos (Liderazgo virtuoso, cap. 'Un programa para ganar' + 'Del temperamento al carácter')
A43: obstáculo | B43: descripción
A44: conformismo | B44: Nadar con la corriente; miedo al qué dirán
A45: perfeccionismo | B45: No aceptar el fallo; abandonar tras el error; fruto del orgullo
A46: impaciencia | B46: Querer que la virtud madure deprisa
A47: falta de realismo | B47: Olvidar que las personas difíciles son colaboradores en nuestro crecimiento
A48: autosatisfacción | B48: Creer que ya se hace bastante
A49: determinismo | B49: Excusar los fallos por el temperamento; negar la libertad
A50: voluntarismo | B50: Negar el temperamento; 'el deber por el deber' contra el corazón
A53: Tipos de reto
A54: tipo | B54: descripción
A55: accion | B55: Hacer algo concreto
A56: omision | B56: No hacer algo: callar, esperar, renunciar
A57: contemplacion | B57: Leer, mirar, escribir, recordar, examinarse

Sheet Resumen
A1: Resumen de la biblioteca
A2: Total de retos | B2: =COUNTA(Retos!A2:A114) -> 113
A4: virtud | B4: nº retos | C4: intensidad media | D4: % del total
A5: prudencia | B5: =COUNTIF(Retos!$D$2:$D$114,A5) -> 13 | C5: =IFERROR(ROUND(AVERAGEIF(Retos!$D$2:$D$114,A5,Retos!$I$2:$I$114),1),"") -> 3.1 | D5: =IFERROR(B5/$B$2,0) -> 0.11504425
A6: fortaleza | B6: =COUNTIF(Retos!$D$2:$D$114,A6) -> 29 | C6: =IFERROR(ROUND(AVERAGEIF(Retos!$D$2:$D$114,A6,Retos!$I$2:$I$114),1),"") -> 3.3 | D6: =IFERROR(B6/$B$2,0) -> 0.25663717
A7: dominio de sí | B7: =COUNTIF(Retos!$D$2:$D$114,A7) -> 15 | C7: =IFERROR(ROUND(AVERAGEIF(Retos!$D$2:$D$114,A7,Retos!$I$2:$I$114),1),"") -> 3.1 | D7: =IFERROR(B7/$B$2,0) -> 0.13274336
A8: justicia | B8: =COUNTIF(Retos!$D$2:$D$114,A8) -> 15 | C8: =IFERROR(ROUND(AVERAGEIF(Retos!$D$2:$D$114,A8,Retos!$I$2:$I$114),1),"") -> 3.2 | D8: =IFERROR(B8/$B$2,0) -> 0.13274336
A9: magnanimidad | B9: =COUNTIF(Retos!$D$2:$D$114,A9) -> 20 | C9: =IFERROR(ROUND(AVERAGEIF(Retos!$D$2:$D$114,A9,Retos!$I$2:$I$114),1),"") -> 3.2 | D9: =IFERROR(B9/$B$2,0) -> 0.17699115
A10: humildad | B10: =COUNTIF(Retos!$D$2:$D$114,A10) -> 21 | C10: =IFERROR(ROUND(AVERAGEIF(Retos!$D$2:$D$114,A10,Retos!$I$2:$I$114),1),"") -> 3.3 | D10: =IFERROR(B10/$B$2,0) -> 0.18584071
A11: Total | B11: =SUM(B5:B10) -> 113
A13: ámbito | B13: nº retos
A14: trabajo | B14: =COUNTIF(Retos!$G$2:$G$114,A14) -> 56
A15: familia | B15: =COUNTIF(Retos!$G$2:$G$114,A15) -> 11
A16: amistad | B16: =COUNTIF(Retos!$G$2:$G$114,A16) -> 10
A17: vida interior | B17: =COUNTIF(Retos!$G$2:$G$114,A17) -> 23
A18: cultura | B18: =COUNTIF(Retos!$G$2:$G$114,A18) -> 5
A19: cuerpo | B19: =COUNTIF(Retos!$G$2:$G$114,A19) -> 3
A20: sociedad | B20: =COUNTIF(Retos!$G$2:$G$114,A20) -> 5
A23: tipo | B23: nº retos
A24: accion | B24: =COUNTIF(Retos!$H$2:$H$114,A24) -> 81
A25: omision | B25: =COUNTIF(Retos!$H$2:$H$114,A25) -> 14
A26: contemplacion | B26: =COUNTIF(Retos!$H$2:$H$114,A26) -> 18
A29: temperamento | B29: retos con dificultad ≥4 (los que más le cuestan) | C29: dificultad media
A30: colérico | B30: =COUNTIF(Retos!$M$2:$M$114,">=4") -> 46 | C30: =ROUND(AVERAGE(Retos!$M$2:$M$114),2) -> 3.14
A31: melancólico | B31: =COUNTIF(Retos!$N$2:$N$114,">=4") -> 47 | C31: =ROUND(AVERAGE(Retos!$N$2:$N$114),2) -> 3.33
A32: sanguíneo | B32: =COUNTIF(Retos!$O$2:$O$114,">=4") -> 36 | C32: =ROUND(AVERAGE(Retos!$O$2:$O$114),2) -> 3.04
A33: flemático | B33: =COUNTIF(Retos!$P$2:$P$114,">=4") -> 40 | C33: =ROUND(AVERAGE(Retos!$P$2:$P$114),2) -> 3.05

Sheet Leyenda
A1: Objeto | B1: Biblioteca de retos diarios derivada de los libros de Alexandre Dianine-Havard (Liderazgo virtuoso, Creado para la grandeza, Del temperamento al carácter, Coaching con Juana de Arco, Corazón libre, Grandir avec son tempérament).
A2: id | B2: Identificador único. Prefijo = virtud o bloque (pru, aud, res, dom, jus, mag, hum, esp = transversal, gt = perfiles combinados).
A3: texto / variante_corta | B3: Reto formulado para hoy, en segunda persona. La variante corta sirve para notificación.
A4: virtud / subcomponente / facultad | B4: Según el marco del método. Facultad: corazón (humildad, magnanimidad), razón (prudencia), voluntad (fortaleza, dominio de sí, justicia).
A5: intensidad | B5: Fórmula: media redondeada de las cuatro dificultades por temperamento. No editar a mano.
A6: dif_* (1–5) | B6: Cuánto cuesta este reto a cada temperamento. 1 = casi natural; 5 = va contra su inclinación. Estimación editorial a partir de los capítulos 'su desafío personal'. Revisable.
A7: disparador_contextual | B7: Situación del día en la que el reto encaja mejor. El motor de selección lo cruza con la agenda del usuario.
A8: obstaculo_que_combate | B8: Uno de los siete obstáculos del catálogo, cuando aplica.
A9: repetible | B9: sí = puede proponerse varias veces en un trimestre; no = reto de una sola vez o de baja frecuencia.
A10: pregunta_examen | B10: Pregunta para el examen de conciencia nocturno; pensada para distinguir fallo de temperamento (primera reacción) y fallo de carácter (decisión).
A11: fuente | B11: Libro, sección y cita breve que respaldan el reto. La cita es orientativa; verificar contra la edición en uso.
A12: Edición | B12: Las celdas de datos tienen validación de lista para virtud, facultad, tipo, ámbito y dificultades (1–5). Añadir filas al final de la tabla 'Retos'; el Resumen se recalcula solo.
